bcp/__init__.py
bcp/config.py
bcp/connections.py
bcp/core.py
bcp/exceptions.py
bcp/files.py
bcp/dialects/base.py
bcp/dialects/mssql.py
bcp-0.4.0.dist-info/LICENSE
bcp-0.4.0.dist-info/WHEEL
bcp-0.4.0.dist-info/METADATA
bcp-0.4.0.dist-info/RECORD
